stockhold/StockCharts_lagacy.py
stockhold/__init__.py
stockhold/__main__.py
stockhold/finance_components.py
stockhold/finance_components_analysis.py
stockhold/finance_components_get_SEC_data.py
stockhold/finance_components_get_data.py
stockhold/flask_app.py
stockhold/stock_analysis.py
stockhold/stock_charts.py
stockhold/common/StockAnalysis_lagacy.py
stockhold/common/data.py
stockhold/common/visualization.py
stockhold/services/StockAnalysis/StockAnalysis.py
stockhold/services/StockAnalysis/StockCharts.py
stockhold/services/StockAnalysis/__init__.py
stockhold/services/dtf/__init__.py
stockhold/services/dtf/dtf.py
stockhold/tests/test_all_analysis_xom.py
stockhold/tests/test_finance_EOD_data.py
stockhold/tests/test_finance_analysis.py
stockhold/tests/test_finance_insider.py
stockhold/tests/test_finance_institution.py
stockhold/tests/test_flask_stock_analysis_for_ticker.py
stockhold/tests/test_flask_stock_analysis_run_all_tickers.py
stockhold/tests/test_sec_data.py
stockhold/tests/test_service_stock_UI_for_ticker.py
stockhold/tests/test_service_stock_analysis_run_all_tickers.py
stockhold/tests/test_stock_analysis_for_ticker.py
stockhold/tests/test_stock_visualization_for_ticker_dropdown.py
stockhold/tests/test_stock_visualization_for_ticker_text_area.py
stockhold-0.0.1.dist-info/LICENSE
stockhold-0.0.1.dist-info/METADATA
stockhold-0.0.1.dist-info/WHEEL
stockhold-0.0.1.dist-info/entry_points.txt
stockhold-0.0.1.dist-info/top_level.txt
stockhold-0.0.1.dist-info/RECORD
