Metadata-Version: 2.1
Name: stockhold
Version: 0.0.1
Summary: stock hold analysis
Author-email: Vamsee Achanta <vamsee.achanta@aceengineer.com>
License: MIT License
Project-URL: repository, https://github.com/vamseeachanta/stockhold
Project-URL: documentation, https://github.com/vamseeachanta/stockhold/blob/main/README.md
Keywords: stock analysis,stock hold,back analysis,investment
Classifier: License :: OSI Approved :: MIT License
Classifier: Programming Language :: Python
Classifier: Programming Language :: Python :: 3
Requires-Python: >=3.7
License-File: LICENSE
Requires-Dist: pandas
Requires-Dist: pyyaml
Requires-Dist: numpy-financial
Requires-Dist: bumpver
Requires-Dist: plotly
Requires-Dist: dash
Requires-Dist: dash-bootstrap-components
Requires-Dist: urllib3
Requires-Dist: xmltodict
Requires-Dist: bs4
Requires-Dist: sqlalchemy
Requires-Dist: yfinance
Requires-Dist: yahoo-fin
Requires-Dist: finvizfinance
Requires-Dist: sec-edgar-downloader
Requires-Dist: ta
Requires-Dist: flask-wtf
Requires-Dist: flask-httpauth
Requires-Dist: flask-restful
Provides-Extra: build
Requires-Dist: build ; extra == 'build'
Requires-Dist: twine ; extra == 'build'
Provides-Extra: dev
Requires-Dist: black ; extra == 'dev'
Requires-Dist: bumpver ; extra == 'dev'
Requires-Dist: isort ; extra == 'dev'
Requires-Dist: mypy ; extra == 'dev'
Requires-Dist: pytest ; extra == 'dev'
